odoo8_addon_shopinvader-8.0.1.0.0.99.dev160-py3.8-nspkg.pth
odoo_addons/shopinvader/README.rst
odoo_addons/shopinvader/__init__.py
odoo_addons/shopinvader/__openerp__.py
odoo_addons/shopinvader/backend.py
odoo_addons/shopinvader/http.py
odoo_addons/shopinvader/controllers/.main.py.swm
odoo_addons/shopinvader/controllers/__init__.py
odoo_addons/shopinvader/controllers/main.py
odoo_addons/shopinvader/data/ir_export_category.xml
odoo_addons/shopinvader/data/ir_export_product.xml
odoo_addons/shopinvader/data/res_partner.xml
odoo_addons/shopinvader/demo/account_demo.xml
odoo_addons/shopinvader/demo/backend_demo.xml
odoo_addons/shopinvader/demo/email_demo.xml
odoo_addons/shopinvader/demo/image_resize_demo.xml
odoo_addons/shopinvader/demo/notification_demo.xml
odoo_addons/shopinvader/demo/partner_demo.xml
odoo_addons/shopinvader/demo/payment_demo.xml
odoo_addons/shopinvader/demo/pricelist_demo.xml
odoo_addons/shopinvader/demo/product_demo.xml
odoo_addons/shopinvader/demo/sale_demo.xml
odoo_addons/shopinvader/i18n/fr.po
odoo_addons/shopinvader/i18n/shopinvader.pot
odoo_addons/shopinvader/models/__init__.py
odoo_addons/shopinvader/models/account_invoice.py
odoo_addons/shopinvader/models/automatic_workflow_job.py
odoo_addons/shopinvader/models/backend.py
odoo_addons/shopinvader/models/ir_http.py
odoo_addons/shopinvader/models/notification.py
odoo_addons/shopinvader/models/partner.py
odoo_addons/shopinvader/models/payment_method.py
odoo_addons/shopinvader/models/product.py
odoo_addons/shopinvader/models/product_category.py
odoo_addons/shopinvader/models/role.py
odoo_addons/shopinvader/models/sale.py
odoo_addons/shopinvader/models/url.py
odoo_addons/shopinvader/security/ir.model.access.csv
odoo_addons/shopinvader/services/__init__.py
odoo_addons/shopinvader/services/abstract_sale.py
odoo_addons/shopinvader/services/address.py
odoo_addons/shopinvader/services/cart.py
odoo_addons/shopinvader/services/cart_item.py
odoo_addons/shopinvader/services/check_vat.py
odoo8_addon_shopinvader-8.0.1.0.0.99.dev160.dist-info/METADATA
odoo8_addon_shopinvader-8.0.1.0.0.99.dev160.dist-info/WHEEL
odoo8_addon_shopinvader-8.0.1.0.0.99.dev160.dist-info/namespace_packages.txt
odoo8_addon_shopinvader-8.0.1.0.0.99.dev160.dist-info/top_level.txt
odoo8_addon_shopinvader-8.0.1.0.0.99.dev160.dist-info/RECORD
