Metadata-Version: 2.1
Name: odoo8-addon-shopinvader
Version: 8.0.1.0.0.99.dev160
Summary: Shopinvader
Home-page: https://akretion.com
Author: Akretion
License: AGPL-3
Platform: UNKNOWN
Classifier: Programming Language :: Python
Classifier: Framework :: Odoo
Classifier: Framework :: Odoo :: 8.0
Classifier: License :: OSI Approved :: GNU Affero General Public License v3
Requires-Python: ~=2.7
Requires-Dist: cerberus
Requires-Dist: odoo8-addon-base-delivery-carrier-label
Requires-Dist: odoo8-addon-base-jsonify
Requires-Dist: odoo8-addon-base-sparse-field
Requires-Dist: odoo8-addon-base-url
Requires-Dist: odoo8-addon-connector-base-product
Requires-Dist: odoo8-addon-connector-locomotivecms
Requires-Dist: odoo8-addon-delivery-carrier-url
Requires-Dist: odoo8-addon-payment-gateway
Requires-Dist: odoo8-addon-product-multi-image
Requires-Dist: odoo8-addon-product-stock-state
Requires-Dist: odoo8-addon-sale-order-line-price-subtotal-gross
Requires-Dist: odoo8-addon-sale-payment-method
Requires-Dist: odoo8-addon-sale-payment-method-automatic-workflow
Requires-Dist: odoo (<9.0a,>=8.0a)
Requires-Dist: pysimplesoap
Requires-Dist: unidecode
